AUTHORS
CHANGELOG.txt
DESCRIPTION
LICENSE
MANIFEST.in
README.rst
setup.py
django_hero_slider.egg-info/PKG-INFO
django_hero_slider.egg-info/SOURCES.txt
django_hero_slider.egg-info/dependency_links.txt
django_hero_slider.egg-info/requires.txt
django_hero_slider.egg-info/top_level.txt
hero_slider/__init__.py
hero_slider/admin.py
hero_slider/models.py
hero_slider/urls.py
hero_slider/views.py
hero_slider/migrations/0001_initial.py
hero_slider/migrations/__init__.py
hero_slider/south_migrations/0001_initial.py
hero_slider/south_migrations/0002_auto__add_field_slideritemtitle_is_published.py
hero_slider/south_migrations/0003_set_existing_slideritems_to_be_published.py
hero_slider/south_migrations/0004_auto__add_field_slideritem_external_url__chg_field_slideritem_object_i.py
hero_slider/south_migrations/0005_auto__add_slideritemcategory__add_slideritemcategorytitle__chg_field_s.py
hero_slider/south_migrations/0006_auto__add_field_slideritem_category.py
hero_slider/south_migrations/0007_hvad_migrations.py
hero_slider/south_migrations/0008_auto__add_field_slideritemtranslation_link_text.py
hero_slider/south_migrations/0009_auto__add_field_slideritem_text_position_top__add_field_slideritem_tex.py
hero_slider/south_migrations/__init__.py
hero_slider/static/hero_slider/js/generic_raw_id_field.js
hero_slider/templates/admin/hero_slider/slideritem/change_form.html
hero_slider/templates/hero_slider/carousel.html
hero_slider/templatetags/__init__.py
hero_slider/templatetags/hero_slider_tags.py
hero_slider/tests/__init__.py
hero_slider/tests/hero_slider_tags_tests.py
hero_slider/tests/models_tests.py
hero_slider/tests/settings.py
hero_slider/tests/test_settings.py
hero_slider/tests/views_tests.py
hero_slider/tests/test_app/__init__.py
hero_slider/tests/test_app/admin.py
hero_slider/tests/test_app/models.py
hero_slider/tests/test_app/urls.py