Metadata-Version: 1.0
Name: django-hero-slider
Version: 1.3
Summary: Django app to define images to be shown on a frontpage slider. They can link to any object.
